xcache.py
xcache-0.2.dist-info/DESCRIPTION.rst
xcache-0.2.dist-info/METADATA
xcache-0.2.dist-info/RECORD
xcache-0.2.dist-info/WHEEL
xcache-0.2.dist-info/metadata.json
xcache-0.2.dist-info/top_level.txt
