Metadata-Version: 2.0
Name: xcache
Version: 0.2
Summary: clean caches when needed
Home-page: https://github.com/srkunze/xcache
Author: Sven R. Kunze
Author-email: srkunze@mail.de
License: MIT
Platform: UNKNOWN
Classifier: Development Status :: 2 - Pre-Alpha
Classifier: Intended Audience :: Developers
Classifier: License :: OSI Approved :: MIT License
Classifier: Programming Language :: Python
